LICENSE
README.md
setup.py
src/bhashini_translator/__init__.py
src/bhashini_translator/bhashini_translator.py
src/bhashini_translator/config.py
src/bhashini_translator/payloads.py
src/bhashini_translator/pipeline_config.py
src/bhashini_translator.egg-info/PKG-INFO
src/bhashini_translator.egg-info/SOURCES.txt
src/bhashini_translator.egg-info/dependency_links.txt
src/bhashini_translator.egg-info/requires.txt
src/bhashini_translator.egg-info/top_level.txt