Metadata-Version: 2.1
Name: bhashini-translator
Version: 0.4
Summary: Python client interface to leverage Bhashini(ULCA) APIs.
Home-page: https://github.com/dteklavya/bhashini_translator
Author: Rajesh Pethe
Author-email: rajesh.pethe@gmail.com
License: UNKNOWN
Platform: UNKNOWN
Requires-Python: >=3.7
License-File: LICENSE
